dispyro/__init__.py
dispyro/dispatcher.py
dispyro/enums.py
dispyro/filters.py
dispyro/handlers.py
dispyro/handlers_holders.py
dispyro/router.py
dispyro/utils.py
dispyro/types/__init__.py
dispyro/types/packed_raw_update.py
dispyro/types/union_types.py
dispyro/types/signatures/__init__.py
dispyro/types/signatures/filter_callback.py
dispyro/types/signatures/handler_callback.py
dispyro-0.2.0.data/data/requirements.txt
dispyro-0.2.0.dist-info/LICENSE
dispyro-0.2.0.dist-info/METADATA
dispyro-0.2.0.dist-info/WHEEL
dispyro-0.2.0.dist-info/top_level.txt
dispyro-0.2.0.dist-info/RECORD
